{"id":"1715793818542-fa6443b8-c97f-4a50-89d3-3203aded7435","testOrder":["de.strullerbaumann.visualee.dependency.boundary.DependencyContainerTest.testFindAllDependenciesWith","de.strullerbaumann.visualee.dependency.boundary.DependencyContainerTest.testGetRelevantClassesDirectlyConnected","de.strullerbaumann.visualee.dependency.boundary.DependencyContainerTest.testGetRelevantClassesFilter","de.strullerbaumann.visualee.dependency.entity.DependencyTypeTest.testIsInverseDirection","de.strullerbaumann.visualee.examiner.ExaminerTest.testCleanPrimitives","de.strullerbaumann.visualee.examiner.ExaminerTest.testCleanupGeneric","de.strullerbaumann.visualee.examiner.ExaminerTest.testCountChar","de.strullerbaumann.visualee.examiner.ExaminerTest.testExtractClassInstanceOrEvent","de.strullerbaumann.visualee.examiner.ExaminerTest.testGetClassBody","de.strullerbaumann.visualee.examiner.ExaminerTest.testGetSourceCodeScanner","de.strullerbaumann.visualee.examiner.ExaminerTest.testIsRelevantType","de.strullerbaumann.visualee.examiner.ExaminerTest.testJumpOverJavaToken","de.strullerbaumann.visualee.examiner.ExaminerTest.testJumpOverTokenInsufficientTokens","de.strullerbaumann.visualee.examiner.ExaminerTest.testScanAfterClosedParenthesis","de.strullerbaumann.visualee.examiner.ExaminerTest.testScanAfterClosedParenthesisInsufficientTokens","de.strullerbaumann.visualee.examiner.ExaminerTest.testScanAfterQuote","de.strullerbaumann.visualee.examiner.ExaminerTest.testisAJavaToken","de.strullerbaumann.visualee.examiner.ExaminerTest.testisAValdiClassName","de.strullerbaumann.visualee.examiner.JavaSourceInspectorTest.testFindAndSetAttributesIgnoreCommentBlocks","de.strullerbaumann.visualee.examiner.JavaSourceInspectorTest.testFindAndSetAttributesIgnoreComments","de.strullerbaumann.visualee.examiner.JavaSourceInspectorTest.testSetGroupNrs","de.strullerbaumann.visualee.examiner.cdi.ExaminerEJBTest.testFindAndSetAttributesEJBSetterWithAnnotations","de.strullerbaumann.visualee.examiner.cdi.ExaminerEJBTest.testFindAndSetAttributesEJBWithParameter","de.strullerbaumann.visualee.examiner.cdi.ExaminerEJBTest.testFindAndSetAttributesSetEJB","de.strullerbaumann.visualee.examiner.cdi.ExaminerEJBTest.testFindAndSetAttributesSetEJBPackageView","de.strullerbaumann.visualee.examiner.cdi.ExaminerEJBTest.testIsRelevantType","de.strullerbaumann.visualee.examiner.cdi.ExaminerEJBTest.testgetTypeFromToken","de.strullerbaumann.visualee.examiner.cdi.ExaminerEventTest.testFindAndSetAttributesSetInstance","de.strullerbaumann.visualee.examiner.cdi.ExaminerEventTest.testFindEvents","de.strullerbaumann.visualee.examiner.cdi.ExaminerEventTest.testIsRelevantType","de.strullerbaumann.visualee.examiner.cdi.ExaminerEventTest.testgetTypeFromToken","de.strullerbaumann.visualee.examiner.cdi.ExaminerInjectTest.testFindAndSetAttributesInjectIgnoreQuotes","de.strullerbaumann.visualee.examiner.cdi.ExaminerInjectTest.testFindAndSetAttributesInjectSetterWithAnnotations","de.strullerbaumann.visualee.examiner.cdi.ExaminerInjectTest.testFindAndSetAttributesSetInject","de.strullerbaumann.visualee.examiner.cdi.ExaminerInjectTest.testFindEventNamedClass","de.strullerbaumann.visualee.examiner.cdi.ExaminerInjectTest.testIsRelevantType","de.strullerbaumann.visualee.examiner.cdi.ExaminerInjectTest.testgetTypeFromToken","de.strullerbaumann.visualee.examiner.cdi.ExaminerInstanceTest.testFindAndSetAttributesSetInstance"],"results":{"de.strullerbaumann.visualee.examiner.ExaminerTest.testGetClassBody":{"name":"de.strullerbaumann.visualee.examiner.ExaminerTest.testGetClassBody","result":"PASS","time":0.015432847,"stackTrace":[]},"de.strullerbaumann.visualee.examiner.cdi.ExaminerInjectTest.testFindAndSetAttributesInjectIgnoreQuotes":{"name":"de.strullerbaumann.visualee.examiner.cdi.ExaminerInjectTest.testFindAndSetAttributesInjectIgnoreQuotes","result":"SKIPPED","time":-1.0,"stackTrace":[]},"de.strullerbaumann.visualee.examiner.cdi.ExaminerInjectTest.testFindAndSetAttributesSetInject":{"name":"de.strullerbaumann.visualee.examiner.cdi.ExaminerInjectTest.testFindAndSetAttributesSetInject","result":"PASS","time":0.001032315,"stackTrace":[]},"de.strullerbaumann.visualee.dependency.boundary.DependencyContainerTest.testGetRelevantClassesFilter":{"name":"de.strullerbaumann.visualee.dependency.boundary.DependencyContainerTest.testGetRelevantClassesFilter","result":"PASS","time":2.0598E-4,"stackTrace":[]},"de.strullerbaumann.visualee.dependency.boundary.DependencyContainerTest.testGetRelevantClassesDirectlyConnected":{"name":"de.strullerbaumann.visualee.dependency.boundary.DependencyContainerTest.testGetRelevantClassesDirectlyConnected","result":"PASS","time":5.02852E-4,"stackTrace":[]},"de.strullerbaumann.visualee.examiner.ExaminerTest.testCleanPrimitives":{"name":"de.strullerbaumann.visualee.examiner.ExaminerTest.testCleanPrimitives","result":"PASS","time":5.75439E-4,"stackTrace":[]},"de.strullerbaumann.visualee.examiner.JavaSourceInspectorTest.testFindAndSetAttributesIgnoreComments":{"name":"de.strullerbaumann.visualee.examiner.JavaSourceInspectorTest.testFindAndSetAttributesIgnoreComments","result":"PASS","time":4.07304E-4,"stackTrace":[]},"de.strullerbaumann.visualee.dependency.entity.DependencyTypeTest.testIsInverseDirection":{"name":"de.strullerbaumann.visualee.dependency.entity.DependencyTypeTest.testIsInverseDirection","result":"PASS","time":8.567E-5,"stackTrace":[]},"de.strullerbaumann.visualee.examiner.ExaminerTest.testisAJavaToken":{"name":"de.strullerbaumann.visualee.examiner.ExaminerTest.testisAJavaToken","result":"PASS","time":6.5909E-5,"stackTrace":[]},"de.strullerbaumann.visualee.examiner.JavaSourceInspectorTest.testFindAndSetAttributesIgnoreCommentBlocks":{"name":"de.strullerbaumann.visualee.examiner.JavaSourceInspectorTest.testFindAndSetAttributesIgnoreCommentBlocks","result":"PASS","time":0.004377214,"stackTrace":[]},"de.strullerbaumann.visualee.examiner.cdi.ExaminerEJBTest.testFindAndSetAttributesSetEJB":{"name":"de.strullerbaumann.visualee.examiner.cdi.ExaminerEJBTest.testFindAndSetAttributesSetEJB","result":"PASS","time":8.41045E-4,"stackTrace":[]},"de.strullerbaumann.visualee.examiner.ExaminerTest.testCleanupGeneric":{"name":"de.strullerbaumann.visualee.examiner.ExaminerTest.testCleanupGeneric","result":"PASS","time":3.3785E-5,"stackTrace":[]},"de.strullerbaumann.visualee.examiner.cdi.ExaminerEJBTest.testFindAndSetAttributesSetEJBPackageView":{"name":"de.strullerbaumann.visualee.examiner.cdi.ExaminerEJBTest.testFindAndSetAttributesSetEJBPackageView","result":"PASS","time":5.22769E-4,"stackTrace":[]},"de.strullerbaumann.visualee.dependency.boundary.DependencyContainerTest.testFindAllDependenciesWith":{"name":"de.strullerbaumann.visualee.dependency.boundary.DependencyContainerTest.testFindAllDependenciesWith","result":"PASS","time":0.003381378,"stackTrace":[]},"de.strullerbaumann.visualee.examiner.cdi.ExaminerInjectTest.testIsRelevantType":{"name":"de.strullerbaumann.visualee.examiner.cdi.ExaminerInjectTest.testIsRelevantType","result":"PASS","time":7.0357E-5,"stackTrace":[]},"de.strullerbaumann.visualee.examiner.ExaminerTest.testisAValdiClassName":{"name":"de.strullerbaumann.visualee.examiner.ExaminerTest.testisAValdiClassName","result":"PASS","time":2.40486E-4,"stackTrace":[]},"de.strullerbaumann.visualee.examiner.ExaminerTest.testIsRelevantType":{"name":"de.strullerbaumann.visualee.examiner.ExaminerTest.testIsRelevantType","result":"PASS","time":1.9654E-5,"stackTrace":[]},"de.strullerbaumann.visualee.examiner.cdi.ExaminerEventTest.testIsRelevantType":{"name":"de.strullerbaumann.visualee.examiner.cdi.ExaminerEventTest.testIsRelevantType","result":"PASS","time":8.028E-5,"stackTrace":[]},"de.strullerbaumann.visualee.examiner.ExaminerTest.testScanAfterQuote":{"name":"de.strullerbaumann.visualee.examiner.ExaminerTest.testScanAfterQuote","result":"PASS","time":7.41862E-4,"stackTrace":[]},"de.strullerbaumann.visualee.examiner.cdi.ExaminerEJBTest.testgetTypeFromToken":{"name":"de.strullerbaumann.visualee.examiner.cdi.ExaminerEJBTest.testgetTypeFromToken","result":"PASS","time":5.7456E-5,"stackTrace":[]},"de.strullerbaumann.visualee.examiner.ExaminerTest.testScanAfterClosedParenthesis":{"name":"de.strullerbaumann.visualee.examiner.ExaminerTest.testScanAfterClosedParenthesis","result":"PASS","time":5.30438E-4,"stackTrace":[]},"de.strullerbaumann.visualee.examiner.ExaminerTest.testCountChar":{"name":"de.strullerbaumann.visualee.examiner.ExaminerTest.testCountChar","result":"PASS","time":4.2382E-5,"stackTrace":[]},"de.strullerbaumann.visualee.examiner.cdi.ExaminerEJBTest.testFindAndSetAttributesEJBWithParameter":{"name":"de.strullerbaumann.visualee.examiner.cdi.ExaminerEJBTest.testFindAndSetAttributesEJBWithParameter","result":"PASS","time":0.001938737,"stackTrace":[]},"de.strullerbaumann.visualee.examiner.cdi.ExaminerEventTest.testFindAndSetAttributesSetInstance":{"name":"de.strullerbaumann.visualee.examiner.cdi.ExaminerEventTest.testFindAndSetAttributesSetInstance","result":"PASS","time":0.001617686,"stackTrace":[]},"de.strullerbaumann.visualee.examiner.JavaSourceInspectorTest.testSetGroupNrs":{"name":"de.strullerbaumann.visualee.examiner.JavaSourceInspectorTest.testSetGroupNrs","result":"PASS","time":6.0355E-5,"stackTrace":[]},"de.strullerbaumann.visualee.examiner.ExaminerTest.testJumpOverJavaToken":{"name":"de.strullerbaumann.visualee.examiner.ExaminerTest.testJumpOverJavaToken","result":"PASS","time":0.001309583,"stackTrace":[]},"de.strullerbaumann.visualee.examiner.cdi.ExaminerInjectTest.testgetTypeFromToken":{"name":"de.strullerbaumann.visualee.examiner.cdi.ExaminerInjectTest.testgetTypeFromToken","result":"PASS","time":4.3118E-5,"stackTrace":[]},"de.strullerbaumann.visualee.examiner.cdi.ExaminerEJBTest.testIsRelevantType":{"name":"de.strullerbaumann.visualee.examiner.cdi.ExaminerEJBTest.testIsRelevantType","result":"PASS","time":1.06299E-4,"stackTrace":[]},"de.strullerbaumann.visualee.examiner.cdi.ExaminerInstanceTest.testFindAndSetAttributesSetInstance":{"name":"de.strullerbaumann.visualee.examiner.cdi.ExaminerInstanceTest.testFindAndSetAttributesSetInstance","result":"PASS","time":9.88469E-4,"stackTrace":[]},"de.strullerbaumann.visualee.examiner.cdi.ExaminerEventTest.testFindEvents":{"name":"de.strullerbaumann.visualee.examiner.cdi.ExaminerEventTest.testFindEvents","result":"PASS","time":8.15284E-4,"stackTrace":[]},"de.strullerbaumann.visualee.examiner.ExaminerTest.testGetSourceCodeScanner":{"name":"de.strullerbaumann.visualee.examiner.ExaminerTest.testGetSourceCodeScanner","result":"PASS","time":2.6914E-5,"stackTrace":[]},"de.strullerbaumann.visualee.examiner.ExaminerTest.testExtractClassInstanceOrEvent":{"name":"de.strullerbaumann.visualee.examiner.ExaminerTest.testExtractClassInstanceOrEvent","result":"PASS","time":3.9922E-5,"stackTrace":[]},"de.strullerbaumann.visualee.examiner.ExaminerTest.testJumpOverTokenInsufficientTokens":{"name":"de.strullerbaumann.visualee.examiner.ExaminerTest.testJumpOverTokenInsufficientTokens","result":"PASS","time":3.51837E-4,"stackTrace":[]},"de.strullerbaumann.visualee.examiner.cdi.ExaminerEventTest.testgetTypeFromToken":{"name":"de.strullerbaumann.visualee.examiner.cdi.ExaminerEventTest.testgetTypeFromToken","result":"PASS","time":4.9663E-5,"stackTrace":[]},"de.strullerbaumann.visualee.examiner.cdi.ExaminerInjectTest.testFindAndSetAttributesInjectSetterWithAnnotations":{"name":"de.strullerbaumann.visualee.examiner.cdi.ExaminerInjectTest.testFindAndSetAttributesInjectSetterWithAnnotations","result":"PASS","time":7.52526E-4,"stackTrace":[]},"de.strullerbaumann.visualee.examiner.cdi.ExaminerEJBTest.testFindAndSetAttributesEJBSetterWithAnnotations":{"name":"de.strullerbaumann.visualee.examiner.cdi.ExaminerEJBTest.testFindAndSetAttributesEJBSetterWithAnnotations","result":"PASS","time":8.90465E-4,"stackTrace":[]},"de.strullerbaumann.visualee.examiner.cdi.ExaminerInjectTest.testFindEventNamedClass":{"name":"de.strullerbaumann.visualee.examiner.cdi.ExaminerInjectTest.testFindEventNamedClass","result":"PASS","time":6.2208E-4,"stackTrace":[]},"de.strullerbaumann.visualee.examiner.ExaminerTest.testScanAfterClosedParenthesisInsufficientTokens":{"name":"de.strullerbaumann.visualee.examiner.ExaminerTest.testScanAfterClosedParenthesisInsufficientTokens","result":"PASS","time":2.84892E-4,"stackTrace":[]}}}