{"id":"1713621537228-aee7f098-4772-47d5-83f1-eceb8aac2a19","testOrder":["org.springframework.cloud.netflix.eureka.server.ApplicationContextTests#adminLoads()","org.springframework.cloud.netflix.eureka.server.ApplicationContextTests#catalogLoads()","org.springframework.cloud.netflix.eureka.server.ApplicationContextTests#cssAvailable()","org.springframework.cloud.netflix.eureka.server.ApplicationContextTests#dashboardLoads()","org.springframework.cloud.netflix.eureka.server.ApplicationContextTests#jsAvailable()","org.springframework.cloud.netflix.eureka.server.ApplicationDashboardDisabledTests#catalogLoads()"],"results":{"org.springframework.cloud.netflix.eureka.server.ApplicationContextTests#jsAvailable()":{"name":"org.springframework.cloud.netflix.eureka.server.ApplicationContextTests#jsAvailable()","result":"PASS","time":0.016463867,"stackTrace":[]},"org.springframework.cloud.netflix.eureka.server.ApplicationContextTests#dashboardLoads()":{"name":"org.springframework.cloud.netflix.eureka.server.ApplicationContextTests#dashboardLoads()","result":"PASS","time":0.187055392,"stackTrace":[]},"org.springframework.cloud.netflix.eureka.server.ApplicationContextTests#catalogLoads()":{"name":"org.springframework.cloud.netflix.eureka.server.ApplicationContextTests#catalogLoads()","result":"PASS","time":0.054229062,"stackTrace":[]},"org.springframework.cloud.netflix.eureka.server.ApplicationContextTests#cssAvailable()":{"name":"org.springframework.cloud.netflix.eureka.server.ApplicationContextTests#cssAvailable()","result":"PASS","time":0.031790943,"stackTrace":[]},"org.springframework.cloud.netflix.eureka.server.ApplicationContextTests#adminLoads()":{"name":"org.springframework.cloud.netflix.eureka.server.ApplicationContextTests#adminLoads()","result":"PASS","time":0.766204209,"stackTrace":[]},"org.springframework.cloud.netflix.eureka.server.ApplicationDashboardDisabledTests#catalogLoads()":{"name":"org.springframework.cloud.netflix.eureka.server.ApplicationDashboardDisabledTests#catalogLoads()","result":"PASS","time":0.01983463,"stackTrace":[]}}}