{"time":{"startTime":1714138257223,"endTime":1714138302054,"elapsedSeconds":44.83099985122681},"status":"FIX_NO_INLINE","dependentTest":"com.j256.ormlite.dao.RuntimeExceptionDaoTest.testCreateOrUpdateThrow","patchResults":[{"time":{"startTime":1714138263685,"endTime":1714138283538,"elapsedSeconds":19.853000164031982},"status":"FIX_NO_INLINE","dependentTest":"com.j256.ormlite.dao.RuntimeExceptionDaoTest.testCreateOrUpdateThrow","polluter":"com.j256.ormlite.logger.LoggerFactoryTest.testSetLogFactory","cleaner":"com.j256.ormlite.logger.LoggerFactoryTest.testLogFactoryProperty","iterations":5,"patchLocation":"/home/alex/Repositories/ormlite-core/.dtfixingtools/fixer/com.j256.ormlite.dao.RuntimeExceptionDaoTest.testCreateOrUpdateThrow.patch"}]}