{"id":"1716000708244-095e7e8b-8e34-416b-97f9-0dae423b4746","testOrder":["hudson.remoting.ChannelTest.testExportCallerDeallocation","hudson.remoting.ChannelTest.testCapability","hudson.remoting.ChannelTest.testDiagnostics","hudson.remoting.ChannelTest.testShouldNotAcceptUserRPCRequestsWhenIsBeingClosed","hudson.remoting.ChannelTest.testGetSetProperty","hudson.remoting.ChannelTest.testClassLoaderHolder","hudson.remoting.ChannelTest.testFailureInDeserialization","hudson.remoting.ChannelTest.testWaitForRemoteProperty","hudson.remoting.ChannelTest.testShouldNotAcceptUserRequestsWhenIsBeingClosed","hudson.remoting.ChannelTest.testExportCalleeDeallocation","hudson.remoting.ChannelTest.testCallSiteStacktrace","hudson.remoting.BinarySafeStreamTest.testRoundtripFlush","hudson.remoting.BinarySafeStreamTest.test1","hudson.remoting.BinarySafeStreamTest.testChunkedWrites","hudson.remoting.BinarySafeStreamTest.testRoundtripNoFlush","hudson.remoting.BinarySafeStreamTest.testSingleWrite","hudson.remoting.PipeTest.testSaturation-local","hudson.remoting.PipeTest.testReaderCloseWhileWriterIsStillWriting-local","hudson.remoting.PipeTest.testLocalWrite-local","hudson.remoting.PipeTest.testLocalWrite2-local","hudson.remoting.PipeTest.testRemoteWrite-local","hudson.remoting.PipeTest.testQuickBurstWrite-local","hudson.remoting.PipeTest.testSaturation-NIO+socket","hudson.remoting.PipeTest.testReaderCloseWhileWriterIsStillWriting-NIO+socket","hudson.remoting.PipeTest.testLocalWrite-NIO+socket","hudson.remoting.PipeTest.testLocalWrite2-NIO+socket","hudson.remoting.PipeTest.testRemoteWrite-NIO+socket","hudson.remoting.PipeTest.testQuickBurstWrite-NIO+socket","hudson.remoting.PipeTest.testSaturation-NIO+pipe","hudson.remoting.PipeTest.testReaderCloseWhileWriterIsStillWriting-NIO+pipe","hudson.remoting.PipeTest.testLocalWrite-NIO+pipe","hudson.remoting.PipeTest.testLocalWrite2-NIO+pipe","hudson.remoting.PipeTest.testRemoteWrite-NIO+pipe","hudson.remoting.PipeTest.testQuickBurstWrite-NIO+pipe","hudson.remoting.PipeTest.testSaturation-local-compatibility","hudson.remoting.PipeTest.testReaderCloseWhileWriterIsStillWriting-local-compatibility","hudson.remoting.PipeTest.testLocalWrite-local-compatibility","hudson.remoting.PipeTest.testLocalWrite2-local-compatibility","hudson.remoting.PipeTest.testRemoteWrite-local-compatibility","hudson.remoting.PipeTest.testQuickBurstWrite-local-compatibility","hudson.remoting.PipeTest.testSaturation-fork","hudson.remoting.PipeTest.testReaderCloseWhileWriterIsStillWriting-fork","hudson.remoting.PipeTest.testLocalWrite-fork","hudson.remoting.PipeTest.testLocalWrite2-fork","hudson.remoting.PipeTest.testRemoteWrite-fork","hudson.remoting.PipeTest.testQuickBurstWrite-fork","hudson.remoting.PipeTest.testSaturation-forkEBCDIC","hudson.remoting.PipeTest.testReaderCloseWhileWriterIsStillWriting-forkEBCDIC","hudson.remoting.PipeTest.testLocalWrite-forkEBCDIC","hudson.remoting.PipeTest.testLocalWrite2-forkEBCDIC","hudson.remoting.PipeTest.testRemoteWrite-forkEBCDIC","hudson.remoting.PipeTest.testQuickBurstWrite-forkEBCDIC","hudson.remoting.LauncherTest.loadDom_Standard","hudson.remoting.LauncherTest.loadDom_EmbeddedDoctype","hudson.remoting.LauncherTest.loadDom_Lol","hudson.remoting.LauncherTest.loadDom_XxeFile","hudson.remoting.LauncherTest.loadDom_XxeHttp","hudson.remoting.PipeWriterTest.testResponseIoCoord","hudson.remoting.PipeWriterTest.testRequestIoCoordClose","hudson.remoting.PipeWriterTest.testRequestIoCoordFlush","hudson.remoting.PipeWriterTest.testRequestIoCoord","hudson.remoting.PipeWriterTest.testResponseIoCoordClose","hudson.remoting.PipeWriterTest.testResponseIoCoordFlush","hudson.remoting.SimpleTest.testCancellation-local","hudson.remoting.SimpleTest.test1-local","hudson.remoting.SimpleTest.test2-local","hudson.remoting.SimpleTest.test3-local","hudson.remoting.SimpleTest.test1Async-local","hudson.remoting.SimpleTest.test2Async-local","hudson.remoting.SimpleTest.testCancellation-NIO+socket","hudson.remoting.SimpleTest.test1-NIO+socket","hudson.remoting.SimpleTest.test2-NIO+socket","hudson.remoting.SimpleTest.test3-NIO+socket","hudson.remoting.SimpleTest.test1Async-NIO+socket","hudson.remoting.SimpleTest.test2Async-NIO+socket","hudson.remoting.SimpleTest.testCancellation-NIO+pipe","hudson.remoting.SimpleTest.test1-NIO+pipe","hudson.remoting.SimpleTest.test2-NIO+pipe","hudson.remoting.SimpleTest.test3-NIO+pipe","hudson.remoting.SimpleTest.test1Async-NIO+pipe","hudson.remoting.SimpleTest.test2Async-NIO+pipe","hudson.remoting.SimpleTest.testCancellation-local-compatibility","hudson.remoting.SimpleTest.test1-local-compatibility","hudson.remoting.SimpleTest.test2-local-compatibility","hudson.remoting.SimpleTest.test3-local-compatibility","hudson.remoting.SimpleTest.test1Async-local-compatibility","hudson.remoting.SimpleTest.test2Async-local-compatibility","hudson.remoting.SimpleTest.testCancellation-fork","hudson.remoting.SimpleTest.test1-fork","hudson.remoting.SimpleTest.test2-fork","hudson.remoting.SimpleTest.test3-fork","hudson.remoting.SimpleTest.test1Async-fork","hudson.remoting.SimpleTest.test2Async-fork","hudson.remoting.SimpleTest.testCancellation-forkEBCDIC","hudson.remoting.SimpleTest.test1-forkEBCDIC","hudson.remoting.SimpleTest.test2-forkEBCDIC","hudson.remoting.SimpleTest.test3-forkEBCDIC","hudson.remoting.SimpleTest.test1Async-forkEBCDIC","hudson.remoting.SimpleTest.test2Async-forkEBCDIC","hudson.remoting.FlightRecorderInputStreamTest.bounding","hudson.remoting.FlightRecorderInputStreamTest.diagnosis","hudson.remoting.PrefetchingTest.testGetResourceAsStream","hudson.remoting.PrefetchingTest.testGetResources"],"results":{"hudson.remoting.SimpleTest.test2-local-compatibility":{"name":"hudson.remoting.SimpleTest.test2-local-compatibility","result":"PASS","time":0.00713435,"stackTrace":[]},"hudson.remoting.SimpleTest.test3-local-compatibility":{"name":"hudson.remoting.SimpleTest.test3-local-compatibility","result":"PASS","time":0.008396559,"stackTrace":[]},"hudson.remoting.PipeTest.testLocalWrite-NIO+socket":{"name":"hudson.remoting.PipeTest.testLocalWrite-NIO+socket","result":"PASS","time":0.086181666,"stackTrace":[]},"hudson.remoting.BinarySafeStreamTest.testSingleWrite":{"name":"hudson.remoting.BinarySafeStreamTest.testSingleWrite","result":"PASS","time":0.002555077,"stackTrace":[]},"hudson.remoting.SimpleTest.testCancellation-NIO+socket":{"name":"hudson.remoting.SimpleTest.testCancellation-NIO+socket","result":"PASS","time":0.047776971,"stackTrace":[]},"hudson.remoting.BinarySafeStreamTest.test1":{"name":"hudson.remoting.BinarySafeStreamTest.test1","result":"PASS","time":1.75127E-4,"stackTrace":[]},"hudson.remoting.SimpleTest.test1-forkEBCDIC":{"name":"hudson.remoting.SimpleTest.test1-forkEBCDIC","result":"PASS","time":1.122623339,"stackTrace":[]},"hudson.remoting.ChannelTest.testGetSetProperty":{"name":"hudson.remoting.ChannelTest.testGetSetProperty","result":"PASS","time":0.017790965,"stackTrace":[]},"hudson.remoting.SimpleTest.test2Async-local":{"name":"hudson.remoting.SimpleTest.test2Async-local","result":"PASS","time":0.004681447,"stackTrace":[]},"hudson.remoting.SimpleTest.test3-NIO+socket":{"name":"hudson.remoting.SimpleTest.test3-NIO+socket","result":"PASS","time":0.066318441,"stackTrace":[]},"hudson.remoting.SimpleTest.test2-local":{"name":"hudson.remoting.SimpleTest.test2-local","result":"PASS","time":0.007957042,"stackTrace":[]},"hudson.remoting.ChannelTest.testExportCallerDeallocation":{"name":"hudson.remoting.ChannelTest.testExportCallerDeallocation","result":"PASS","time":1.902346622,"stackTrace":[]},"hudson.remoting.PipeTest.testRemoteWrite-fork":{"name":"hudson.remoting.PipeTest.testRemoteWrite-fork","result":"PASS","time":1.162522409,"stackTrace":[]},"hudson.remoting.LauncherTest.loadDom_Standard":{"name":"hudson.remoting.LauncherTest.loadDom_Standard","result":"PASS","time":0.026723252,"stackTrace":[]},"hudson.remoting.PipeTest.testLocalWrite-local":{"name":"hudson.remoting.PipeTest.testLocalWrite-local","result":"PASS","time":0.068562807,"stackTrace":[]},"hudson.remoting.PipeWriterTest.testResponseIoCoordFlush":{"name":"hudson.remoting.PipeWriterTest.testResponseIoCoordFlush","result":"PASS","time":3.027582938,"stackTrace":[]},"hudson.remoting.SimpleTest.test2Async-NIO+pipe":{"name":"hudson.remoting.SimpleTest.test2Async-NIO+pipe","result":"PASS","time":0.015965964,"stackTrace":[]},"hudson.remoting.ChannelTest.testCapability":{"name":"hudson.remoting.ChannelTest.testCapability","result":"PASS","time":0.005674625,"stackTrace":[]},"hudson.remoting.SimpleTest.test3-NIO+pipe":{"name":"hudson.remoting.SimpleTest.test3-NIO+pipe","result":"PASS","time":0.024761101,"stackTrace":[]},"hudson.remoting.SimpleTest.test1-local":{"name":"hudson.remoting.SimpleTest.test1-local","result":"PASS","time":0.018525206,"stackTrace":[]},"hudson.remoting.PipeTest.testLocalWrite2-NIO+socket":{"name":"hudson.remoting.PipeTest.testLocalWrite2-NIO+socket","result":"PASS","time":2.150164021,"stackTrace":[]},"hudson.remoting.PipeTest.testRemoteWrite-local":{"name":"hudson.remoting.PipeTest.testRemoteWrite-local","result":"PASS","time":0.035534908,"stackTrace":[]},"hudson.remoting.PipeTest.testLocalWrite-NIO+pipe":{"name":"hudson.remoting.PipeTest.testLocalWrite-NIO+pipe","result":"PASS","time":0.040965126,"stackTrace":[]},"hudson.remoting.SimpleTest.test2-forkEBCDIC":{"name":"hudson.remoting.SimpleTest.test2-forkEBCDIC","result":"PASS","time":1.048116946,"stackTrace":[]},"hudson.remoting.PipeWriterTest.testResponseIoCoord":{"name":"hudson.remoting.PipeWriterTest.testResponseIoCoord","result":"PASS","time":3.020663735,"stackTrace":[]},"hudson.remoting.SimpleTest.test1-NIO+socket":{"name":"hudson.remoting.SimpleTest.test1-NIO+socket","result":"PASS","time":0.046246252,"stackTrace":[]},"hudson.remoting.PipeTest.testQuickBurstWrite-forkEBCDIC":{"name":"hudson.remoting.PipeTest.testQuickBurstWrite-forkEBCDIC","result":"PASS","time":1.101005051,"stackTrace":[]},"hudson.remoting.SimpleTest.test3-fork":{"name":"hudson.remoting.SimpleTest.test3-fork","result":"PASS","time":1.10281419,"stackTrace":[]},"hudson.remoting.SimpleTest.test2-NIO+pipe":{"name":"hudson.remoting.SimpleTest.test2-NIO+pipe","result":"PASS","time":0.022854556,"stackTrace":[]},"hudson.remoting.ChannelTest.testShouldNotAcceptUserRequestsWhenIsBeingClosed":{"name":"hudson.remoting.ChannelTest.testShouldNotAcceptUserRequestsWhenIsBeingClosed","result":"PASS","time":1.046352956,"stackTrace":[]},"hudson.remoting.PipeTest.testQuickBurstWrite-local":{"name":"hudson.remoting.PipeTest.testQuickBurstWrite-local","result":"PASS","time":0.016669047,"stackTrace":[]},"hudson.remoting.SimpleTest.testCancellation-fork":{"name":"hudson.remoting.SimpleTest.testCancellation-fork","result":"PASS","time":1.077057118,"stackTrace":[]},"hudson.remoting.ChannelTest.testDiagnostics":{"name":"hudson.remoting.ChannelTest.testDiagnostics","result":"PASS","time":0.016586877,"stackTrace":[]},"hudson.remoting.PipeTest.testQuickBurstWrite-NIO+pipe":{"name":"hudson.remoting.PipeTest.testQuickBurstWrite-NIO+pipe","result":"PASS","time":0.007100728,"stackTrace":[]},"hudson.remoting.PipeTest.testReaderCloseWhileWriterIsStillWriting-fork":{"name":"hudson.remoting.PipeTest.testReaderCloseWhileWriterIsStillWriting-fork","result":"PASS","time":1.109837495,"stackTrace":[]},"hudson.remoting.PipeTest.testLocalWrite-local-compatibility":{"name":"hudson.remoting.PipeTest.testLocalWrite-local-compatibility","result":"PASS","time":0.069899598,"stackTrace":[]},"hudson.remoting.PipeTest.testReaderCloseWhileWriterIsStillWriting-NIO+socket":{"name":"hudson.remoting.PipeTest.testReaderCloseWhileWriterIsStillWriting-NIO+socket","result":"PASS","time":0.072844041,"stackTrace":[]},"hudson.remoting.SimpleTest.testCancellation-forkEBCDIC":{"name":"hudson.remoting.SimpleTest.testCancellation-forkEBCDIC","result":"PASS","time":1.068429777,"stackTrace":[]},"hudson.remoting.PipeTest.testQuickBurstWrite-NIO+socket":{"name":"hudson.remoting.PipeTest.testQuickBurstWrite-NIO+socket","result":"PASS","time":0.092392876,"stackTrace":[]},"hudson.remoting.SimpleTest.test2Async-NIO+socket":{"name":"hudson.remoting.SimpleTest.test2Async-NIO+socket","result":"PASS","time":0.062604632,"stackTrace":[]},"hudson.remoting.SimpleTest.test1-local-compatibility":{"name":"hudson.remoting.SimpleTest.test1-local-compatibility","result":"PASS","time":0.007844631,"stackTrace":[]},"hudson.remoting.LauncherTest.loadDom_Lol":{"name":"hudson.remoting.LauncherTest.loadDom_Lol","result":"PASS","time":0.001580693,"stackTrace":[]},"hudson.remoting.ChannelTest.testWaitForRemoteProperty":{"name":"hudson.remoting.ChannelTest.testWaitForRemoteProperty","result":"PASS","time":0.527937081,"stackTrace":[]},"hudson.remoting.PipeTest.testSaturation-forkEBCDIC":{"name":"hudson.remoting.PipeTest.testSaturation-forkEBCDIC","result":"PASS","time":2.124465093,"stackTrace":[]},"hudson.remoting.SimpleTest.testCancellation-NIO+pipe":{"name":"hudson.remoting.SimpleTest.testCancellation-NIO+pipe","result":"PASS","time":0.016433163,"stackTrace":[]},"hudson.remoting.PipeTest.testRemoteWrite-NIO+socket":{"name":"hudson.remoting.PipeTest.testRemoteWrite-NIO+socket","result":"PASS","time":0.083782688,"stackTrace":[]},"hudson.remoting.PipeTest.testSaturation-local-compatibility":{"name":"hudson.remoting.PipeTest.testSaturation-local-compatibility","result":"PASS","time":0.006685598,"stackTrace":[]},"hudson.remoting.PrefetchingTest.testGetResourceAsStream":{"name":"hudson.remoting.PrefetchingTest.testGetResourceAsStream","result":"PASS","time":0.074108994,"stackTrace":[]},"hudson.remoting.PipeTest.testLocalWrite-fork":{"name":"hudson.remoting.PipeTest.testLocalWrite-fork","result":"PASS","time":1.165808632,"stackTrace":[]},"hudson.remoting.PipeTest.testRemoteWrite-NIO+pipe":{"name":"hudson.remoting.PipeTest.testRemoteWrite-NIO+pipe","result":"PASS","time":0.032761329,"stackTrace":[]},"hudson.remoting.PipeWriterTest.testResponseIoCoordClose":{"name":"hudson.remoting.PipeWriterTest.testResponseIoCoordClose","result":"PASS","time":3.027639835,"stackTrace":[]},"hudson.remoting.PipeWriterTest.testRequestIoCoordFlush":{"name":"hudson.remoting.PipeWriterTest.testRequestIoCoordFlush","result":"PASS","time":3.034938513,"stackTrace":[]},"hudson.remoting.PrefetchingTest.testGetResources":{"name":"hudson.remoting.PrefetchingTest.testGetResources","result":"PASS","time":0.045877626,"stackTrace":[]},"hudson.remoting.PipeTest.testReaderCloseWhileWriterIsStillWriting-NIO+pipe":{"name":"hudson.remoting.PipeTest.testReaderCloseWhileWriterIsStillWriting-NIO+pipe","result":"PASS","time":0.029100077,"stackTrace":[]},"hudson.remoting.PipeTest.testLocalWrite2-local":{"name":"hudson.remoting.PipeTest.testLocalWrite2-local","result":"PASS","time":2.070005094,"stackTrace":[]},"hudson.remoting.PipeTest.testRemoteWrite-forkEBCDIC":{"name":"hudson.remoting.PipeTest.testRemoteWrite-forkEBCDIC","result":"PASS","time":1.141799642,"stackTrace":[]},"hudson.remoting.PipeWriterTest.testRequestIoCoord":{"name":"hudson.remoting.PipeWriterTest.testRequestIoCoord","result":"PASS","time":3.034798255,"stackTrace":[]},"hudson.remoting.SimpleTest.test2Async-forkEBCDIC":{"name":"hudson.remoting.SimpleTest.test2Async-forkEBCDIC","result":"PASS","time":1.058198249,"stackTrace":[]},"hudson.remoting.LauncherTest.loadDom_EmbeddedDoctype":{"name":"hudson.remoting.LauncherTest.loadDom_EmbeddedDoctype","result":"PASS","time":0.006935085,"stackTrace":[]},"hudson.remoting.PipeTest.testLocalWrite2-NIO+pipe":{"name":"hudson.remoting.PipeTest.testLocalWrite2-NIO+pipe","result":"PASS","time":2.059378957,"stackTrace":[]},"hudson.remoting.PipeTest.testReaderCloseWhileWriterIsStillWriting-forkEBCDIC":{"name":"hudson.remoting.PipeTest.testReaderCloseWhileWriterIsStillWriting-forkEBCDIC","result":"PASS","time":1.147012061,"stackTrace":[]},"hudson.remoting.SimpleTest.test1Async-local-compatibility":{"name":"hudson.remoting.SimpleTest.test1Async-local-compatibility","result":"PASS","time":0.0053041,"stackTrace":[]},"hudson.remoting.PipeTest.testReaderCloseWhileWriterIsStillWriting-local":{"name":"hudson.remoting.PipeTest.testReaderCloseWhileWriterIsStillWriting-local","result":"PASS","time":0.056075694,"stackTrace":[]},"hudson.remoting.BinarySafeStreamTest.testRoundtripFlush":{"name":"hudson.remoting.BinarySafeStreamTest.testRoundtripFlush","result":"PASS","time":0.235518973,"stackTrace":[]},"hudson.remoting.PipeTest.testLocalWrite2-forkEBCDIC":{"name":"hudson.remoting.PipeTest.testLocalWrite2-forkEBCDIC","result":"PASS","time":3.076047359,"stackTrace":[]},"hudson.remoting.SimpleTest.test2-NIO+socket":{"name":"hudson.remoting.SimpleTest.test2-NIO+socket","result":"PASS","time":0.051591061,"stackTrace":[]},"hudson.remoting.PipeTest.testSaturation-NIO+socket":{"name":"hudson.remoting.PipeTest.testSaturation-NIO+socket","result":"PASS","time":1.334325485,"stackTrace":[]},"hudson.remoting.PipeTest.testSaturation-NIO+pipe":{"name":"hudson.remoting.PipeTest.testSaturation-NIO+pipe","result":"PASS","time":1.105021447,"stackTrace":[]},"hudson.remoting.SimpleTest.test1Async-NIO+pipe":{"name":"hudson.remoting.SimpleTest.test1Async-NIO+pipe","result":"PASS","time":0.01812235,"stackTrace":[]},"hudson.remoting.SimpleTest.test3-local":{"name":"hudson.remoting.SimpleTest.test3-local","result":"PASS","time":0.009608681,"stackTrace":[]},"hudson.remoting.SimpleTest.test1Async-forkEBCDIC":{"name":"hudson.remoting.SimpleTest.test1Async-forkEBCDIC","result":"PASS","time":1.05688648,"stackTrace":[]},"hudson.remoting.BinarySafeStreamTest.testRoundtripNoFlush":{"name":"hudson.remoting.BinarySafeStreamTest.testRoundtripNoFlush","result":"PASS","time":0.101830016,"stackTrace":[]},"hudson.remoting.PipeTest.testSaturation-fork":{"name":"hudson.remoting.PipeTest.testSaturation-fork","result":"PASS","time":2.171117601,"stackTrace":[]},"hudson.remoting.ChannelTest.testClassLoaderHolder":{"name":"hudson.remoting.ChannelTest.testClassLoaderHolder","result":"PASS","time":0.017489278,"stackTrace":[]},"hudson.remoting.SimpleTest.test1-fork":{"name":"hudson.remoting.SimpleTest.test1-fork","result":"PASS","time":1.035147689,"stackTrace":[]},"hudson.remoting.SimpleTest.testCancellation-local-compatibility":{"name":"hudson.remoting.SimpleTest.testCancellation-local-compatibility","result":"PASS","time":0.011666066,"stackTrace":[]},"hudson.remoting.PipeTest.testLocalWrite-forkEBCDIC":{"name":"hudson.remoting.PipeTest.testLocalWrite-forkEBCDIC","result":"PASS","time":1.149592363,"stackTrace":[]},"hudson.remoting.PipeTest.testQuickBurstWrite-local-compatibility":{"name":"hudson.remoting.PipeTest.testQuickBurstWrite-local-compatibility","result":"PASS","time":0.007156602,"stackTrace":[]},"hudson.remoting.PipeWriterTest.testRequestIoCoordClose":{"name":"hudson.remoting.PipeWriterTest.testRequestIoCoordClose","result":"PASS","time":3.034403231,"stackTrace":[]},"hudson.remoting.SimpleTest.test2Async-fork":{"name":"hudson.remoting.SimpleTest.test2Async-fork","result":"PASS","time":1.06991021,"stackTrace":[]},"hudson.remoting.LauncherTest.loadDom_XxeHttp":{"name":"hudson.remoting.LauncherTest.loadDom_XxeHttp","result":"PASS","time":0.001841974,"stackTrace":[]},"hudson.remoting.SimpleTest.test3-forkEBCDIC":{"name":"hudson.remoting.SimpleTest.test3-forkEBCDIC","result":"PASS","time":1.084399026,"stackTrace":[]},"hudson.remoting.FlightRecorderInputStreamTest.diagnosis":{"name":"hudson.remoting.FlightRecorderInputStreamTest.diagnosis","result":"PASS","time":0.002412061,"stackTrace":[]},"hudson.remoting.PipeTest.testSaturation-local":{"name":"hudson.remoting.PipeTest.testSaturation-local","result":"PASS","time":1.073110182,"stackTrace":[]},"hudson.remoting.ChannelTest.testShouldNotAcceptUserRPCRequestsWhenIsBeingClosed":{"name":"hudson.remoting.ChannelTest.testShouldNotAcceptUserRPCRequestsWhenIsBeingClosed","result":"PASS","time":1.043216761,"stackTrace":[]},"hudson.remoting.LauncherTest.loadDom_XxeFile":{"name":"hudson.remoting.LauncherTest.loadDom_XxeFile","result":"PASS","time":0.00283552,"stackTrace":[]},"hudson.remoting.SimpleTest.test1Async-NIO+socket":{"name":"hudson.remoting.SimpleTest.test1Async-NIO+socket","result":"PASS","time":0.060711473,"stackTrace":[]},"hudson.remoting.ChannelTest.testExportCalleeDeallocation":{"name":"hudson.remoting.ChannelTest.testExportCalleeDeallocation","result":"PASS","time":1.294617049,"stackTrace":[]},"hudson.remoting.SimpleTest.test1Async-local":{"name":"hudson.remoting.SimpleTest.test1Async-local","result":"PASS","time":0.004907307,"stackTrace":[]},"hudson.remoting.SimpleTest.test1Async-fork":{"name":"hudson.remoting.SimpleTest.test1Async-fork","result":"PASS","time":1.03825518,"stackTrace":[]},"hudson.remoting.BinarySafeStreamTest.testChunkedWrites":{"name":"hudson.remoting.BinarySafeStreamTest.testChunkedWrites","result":"PASS","time":0.048439572,"stackTrace":[]},"hudson.remoting.SimpleTest.test2Async-local-compatibility":{"name":"hudson.remoting.SimpleTest.test2Async-local-compatibility","result":"PASS","time":0.005350786,"stackTrace":[]},"hudson.remoting.PipeTest.testRemoteWrite-local-compatibility":{"name":"hudson.remoting.PipeTest.testRemoteWrite-local-compatibility","result":"PASS","time":0.064629686,"stackTrace":[]},"hudson.remoting.FlightRecorderInputStreamTest.bounding":{"name":"hudson.remoting.FlightRecorderInputStreamTest.bounding","result":"PASS","time":0.016322484,"stackTrace":[]},"hudson.remoting.PipeTest.testReaderCloseWhileWriterIsStillWriting-local-compatibility":{"name":"hudson.remoting.PipeTest.testReaderCloseWhileWriterIsStillWriting-local-compatibility","result":"PASS","time":0.029464277,"stackTrace":[]},"hudson.remoting.SimpleTest.test1-NIO+pipe":{"name":"hudson.remoting.SimpleTest.test1-NIO+pipe","result":"PASS","time":0.022601924,"stackTrace":[]},"hudson.remoting.ChannelTest.testCallSiteStacktrace":{"name":"hudson.remoting.ChannelTest.testCallSiteStacktrace","result":"PASS","time":0.044448951,"stackTrace":[]},"hudson.remoting.PipeTest.testLocalWrite2-local-compatibility":{"name":"hudson.remoting.PipeTest.testLocalWrite2-local-compatibility","result":"PASS","time":2.084830997,"stackTrace":[]},"hudson.remoting.ChannelTest.testFailureInDeserialization":{"name":"hudson.remoting.ChannelTest.testFailureInDeserialization","result":"PASS","time":0.018467583,"stackTrace":[]},"hudson.remoting.PipeTest.testQuickBurstWrite-fork":{"name":"hudson.remoting.PipeTest.testQuickBurstWrite-fork","result":"PASS","time":1.096904871,"stackTrace":[]},"hudson.remoting.PipeTest.testLocalWrite2-fork":{"name":"hudson.remoting.PipeTest.testLocalWrite2-fork","result":"PASS","time":3.141413662,"stackTrace":[]},"hudson.remoting.SimpleTest.testCancellation-local":{"name":"hudson.remoting.SimpleTest.testCancellation-local","result":"PASS","time":0.021736144,"stackTrace":[]},"hudson.remoting.SimpleTest.test2-fork":{"name":"hudson.remoting.SimpleTest.test2-fork","result":"PASS","time":1.109453067,"stackTrace":[]}}}